Workbook

Sheet Cover
B2: SAIPEM–SUBSEA7 HISTORICAL FINANCIALS WORKBOOK
B4: Prepared by: Khalil Bourgou
B5: Period covered: FY2020 – FY2025
B6: Source documents: Saipem Annual Reports 2020–2025; Subsea 7 S.A. Annual Reports 2020–2025
B7: Reporting currencies: Saipem in EUR (€ million); Subsea7 in USD ($ million)
B9: PURPOSE
B10: Clean starting-point workbook for a Saipem–Subsea7 merger and pro-forma valuation project. All figures are linked to a shared FX sheet so the workbook can be presented in either currency.
B12: SHEET GUIDE
B13: • FX — Year-end and average EUR/USD rates. All cross-currency conversions reference this sheet.
B14: • Saipem_IS — Income statement, € million, 2020–2025. Six-year historical.
B15: • Saipem_BS — Reclassified balance sheet, € million, as of 31 December each year.
B16: • Saipem_CF — Reclassified cash flow, € million, 2020–2025.
... B40: • MAJOR EVENT: In February 2025 Saipem announced a merger MoU with Subsea7 (binding merger agreement subsequently signed). This workbook is scoped as pre-merger historicals — pro-forma modelling is a separate exercise.

Sheet FX
A1: FX RATES — EUR/USD
B3: 2020 | C3: 2021 | D3: 2022 | E3: 2023 | F3: 2024 | G3: 2025
A4: EUR/USD — year-end (31 Dec) | B4: 1.2271 | C4: 1.1326 | D4: 1.0666 | E4: 1.105 | F4: 1.0389 | G4: 1.183
A5: EUR/USD — annual average | B5: 1.1422 | C5: 1.1827 | D5: 1.053 | E5: 1.0813 | F5: 1.0824 | G5: 1.133
A7: USD/EUR — year-end (implied) | B7: =1/B4 -> 0.81492951 | C7: =1/C4 -> 0.88292425 | D7: =1/D4 -> 0.9375586 | E7: =1/E4 -> 0.90497738 | F7: =1/F4 -> 0.96255655 | G7: =1/G4 -> 0.84530854
A8: USD/EUR — annual average (implied) | B8: =1/B5 -> 0.87550341 | C8: =1/C5 -> 0.84552296 | D8: =1/D5 -> 0.94966762 | E8: =1/E5 -> 0.92481273 | F8: =1/F5 -> 0.92387288 | G8: =1/G5 -> 0.88261253
A10: Note: P&L items should be translated at the annual average; balance-sheet items at year-end.

Sheet Saipem_IS
A1: SAIPEM — CONSOLIDATED INCOME STATEMENT (€ million)
B3: 2020 | C3: 2021 | D3: 2022 | E3: 2023 | F3: 2024 | G3: 2025
A4: Core business revenue | B4: 7342 | C4: 6528 | D4: 9980 | E4: 11874 | F4: 14549 | G4: 15497
A5: Other revenue and income | B5: 12 | C5: 5 | D5: 9 | E5: 23 | F5: 3 | G5: 5
A6: Purchases, services and other costs | B6: -5294 | C6: -6662 | D6: -7822 | E6: -9236 | F6: -11160 | G6: -11570
A7: Net impairment losses on trade receivables | B7: -7 | C7: -42 | D7: 32 | E7: 1 | F7: -5 | G7: 33
A8: Personnel expenses | B8: -1625 | C8: -1553 | D8: -1656 | E8: -1736 | F8: -2058 | G8: -2249
A9: EBITDA (computed) | B9: =SUM(B4:B8) -> 428 | C9: =SUM(C4:C8) -> -1724 | D9: =SUM(D4:D8) -> 543 | E9: =SUM(E4:E8) -> 926 | F9: =SUM(F4:F8) -> 1329 | G9: =SUM(G4:G8) -> 1716
A10: EBITDA (as reported) | B10: 428 | C10: -1724 | D10: 543 | E10: 926 | F10: 1329 | G10: 1716
A11: Depreciation, amortisation and impairment | B11: -1273 | C11: -495 | D11: -445 | E11: -489 | F11: -723 | G11: -1037
A12: Operating result (EBIT) | B12: -845 | C12: -2219 | D12: 98 | E12: 437 | F12: 606 | G12: 679
A13: Net financial income (expense) | B13: -166 | C13: -137 | D13: -195 | E13: -167 | F13: -85 | G13: -189
A14: Net gains (losses) on equity investments | B14: 37 | C14: 9 | D14: -65 | E14: 60 | F14: -25 | G14: 28
A15: Pre-tax profit (loss) | B15: -974 | C15: -2347 | D15: -162 | E15: 330 | F15: 496 | G15: 518
A16: Income taxes | B16: -143 | C16: -59 | D16: -153 | E16: -145 | F16: -190 | G16: -207
A17: Profit (loss) before non-controlling interests | B17: -1117 | C17: -2406 | D17: -315 | E17: 185 | F17: 306 | G17: 311
A18: Non-controlling interests | B18: -19 | C18: 0 | D18: 0 | E18: 0 | F18: 0 | G18: -1
A19: Profit (loss) for the year — Continuing ops | B19: -1136 | C19: -2406 | D19: -315 | E19: 185 | F19: 306 | G19: 310
A21: MARGINS
A22: EBITDA margin | B22: =B10/B4 -> 0.058294743 | C22: =C10/C4 -> -0.26409314 | D22: =D10/D4 -> 0.054408818 | E22: =E10/E4 -> 0.077985515 | F22: =F10/F4 -> 0.091346484 | G22: =G10/G4 -> 0.11073111
A23: EBIT margin | B23: =B12/B4 -> -0.11509126 | C23: =C12/C4 -> -0.33992034 | D23: =D12/D4 -> 0.0098196393 | E23: =E12/E4 -> 0.036803099 | F23: =F12/F4 -> 0.041652347 | G23: =G12/G4 -> 0.043814932
A24: Net margin | B24: =B19/B4 -> -0.15472623 | C24: =C19/C4 -> -0.36856618 | D24: =D19/D4 -> -0.031563126 | E24: =E19/E4 -> 0.015580259 | F24: =F19/F4 -> 0.021032373 | G24: =G19/G4 -> 0.020003872
A25: Revenue YoY growth | C25: =C4/B4-1 -> -0.11086897 | D25: =D4/C4-1 -> 0.52879902 | E25: =E4/D4-1 -> 0.18977956 | F25: =F4/E4-1 -> 0.22528213 | G25: =G4/F4-1 -> 0.065159117

Sheet Saipem_BS
A1: SAIPEM — RECLASSIFIED BALANCE SHEET (€ million, as of 31 December)
B3: 2020 | C3: 2021 | D3: 2022 | E3: 2023 | F3: 2024 | G3: 2025
A4: USES OF FUNDS
A5: Property, plant and equipment | B5: 3284 | C5: 3113 | D5: 2879 | E5: 2960 | F5: 2844 | G5: 2700
A6: Right-of-use of lease assets | B6: 288 | C6: 261 | D6: 258 | E6: 428 | F6: 630 | G6: 1213
A7: Net intangible assets | B7: 701 | C7: 699 | D7: 691 | E7: 666 | F7: 668 | G7: 38
A8: Goodwill (disclosed separately 2025) | B8: 0 | C8: 0 | D8: 0 | E8: 0 | F8: 0 | G8: 641
A9: Equity investments | B9: 140 | C9: 127 | D9: 128 | E9: 162 | F9: -14 | G9: -25
A10: Non-current assets | B10: 4413 | C10: 4200 | D10: 3956 | E10: 4216 | F10: 4128 | G10: 4567
A11: Net current assets (liabilities) | B11: -2 | C11: -2070 | D11: -1589 | E11: -1366 | F11: -1508 | G11: -1462
A12: Employee benefits | B12: -237 | C12: -238 | D12: -183 | E12: -193 | F12: -208 | G12: -195
A13: Net assets held for sale | B13: 0 | C13: 0 | D13: 166 | E13: 0 | F13: 89 | G13: 0
A14: Net capital employed | B14: 4174 | C14: 1892 | D14: 2350 | E14: 2657 | F14: 2501 | G14: 2910
A16: SOURCES OF FUNDS
A17: Equity | B17: 2923 | C17: 326 | D17: 2068 | E17: 2394 | F17: 2524 | G17: 2637
A18: Non-controlling interests | B18: 25 | C18: 25 | D18: 18 | E18: 2 | F18: 0 | G18: 1
A19: Net financial debt pre-IFRS 16 | B19: 872 | C19: 1223 | D19: -56 | E19: -216 | F19: -683 | G19: -999
A20: Lease liabilities (IFRS 16) | B20: 354 | C20: 318 | D20: 320 | E20: 477 | F20: 660 | G20: 1271
A21: Net financial debt post-IFRS 16 | B21: 1226 | C21: 1541 | D21: 264 | E21: 261 | F21: -23 | G21: 272
A22: Funding (check vs Net capital employed) | B22: =B17+B18+B21 -> 4174 | C22: =C17+C18+C21 -> 1892 | D22: =D17+D18+D21 -> 2350 | E22: =E17+E18+E21 -> 2657 | F22: =F17+F18+F21 -> 2501 | G22: =G17+G18+G21 -> 2910
A24: CAPITAL STRUCTURE RATIOS
A25: Leverage pre-IFRS 16 (Net debt / Equity+NCI) | B25: =B19/(B17+B18) -> 0.29579376 | C25: =C19/(C17+C18) -> 3.4843305 | D25: =D19/(D17+D18) -> -0.026845638 | E25: =E19/(E17+E18) -> -0.09015025 | F25: =F19/(F17+F18) -> -0.27060222 | G25: =G19/(G17+G18) -> -0.37869598
A26: Leverage post-IFRS 16 (Net debt / Equity+NCI) | B26: =B21/(B17+B18) -> 0.41587517 | C26: =C21/(C17+C18) -> 4.3903134 | D26: =D21/(D17+D18) -> 0.12655801 | E26: =E21/(E17+E18) -> 0.10893155 | F26: =F21/(F17+F18) -> -0.0091125198 | G26: =G21/(G17+G18) -> 0.10310842

Sheet Saipem_CF
A1: SAIPEM — RECLASSIFIED CASH FLOW (€ million)
B3: 2020 | C3: 2021 | D3: 2022 | E3: 2023 | F3: 2024 | G3: 2025
A4: Profit (loss) for the year | B4: -1136 | C4: -2467 | D4: -209 | E4: 179 | F4: 306 | G4: 310
A5: Non-controlling interests | B5: 19 | C5: 0 | D5: 0 | E5: 0 | F5: 0 | G5: 1
A6: Depreciation, amortisation, other non-monetary items | B6: 1316 | C6: 477 | D6: 375 | E6: 413 | F6: 806 | G6: 1065
A7: Net (gains) losses on disposals | B7: -8 | C7: 0 | D7: -121 | E7: 34 | F7: -18 | G7: -17
A8: Dividends, interest and income taxes | B8: 272 | C8: 184 | D8: 287 | E8: 252 | F8: 283 | G8: 301
A9: Cash flow from ops before WC changes | B9: 463 | C9: -1806 | D9: 226 | E9: 884 | F9: 1377 | G9: 1660
A10: Changes in working capital | B10: -72 | C10: 2081 | D10: -624 | E10: -134 | F10: -56 | G10: 129
A11: Dividends received, taxes/interest paid | B11: -268 | C11: -185 | D11: -244 | E11: -164 | F11: -260 | G11: -285
A12: Net cash from operating activities — Continuing | B12: 123 | C12: 90 | D12: -523 | E12: 586 | F12: 1061 | G12: 1504
A13: Net cash from operating activities — Discontinued | B13: 0 | C13: 0 | D13: 46 | E13: 0 | F13: 0 | G13: 0
A14: Net cash from operating activities — Total | B14: 123 | C14: 90 | D14: -477 | E14: 586 | F14: 1061 | G14: 1504
A15: Capital expenditure — Continuing | B15: -322 | C15: -298 | D15: -523 | E15: -482 | F15: -337 | G15: -364
... A20: Free cash flow (as reported) | B20: -187 | C20: -193 | D20: -524 | E20: 248 | F20: 757 | G20: 1241
A22: FCF conversion (FCF / EBITDA) | B22: =IFERROR(B20/Saipem_IS!B10,"") -> -0.43691589 | C22: =IFERROR(C20/Saipem_IS!C10,"") -> 0.11194896 | D22: =IFERROR(D20/Saipem_IS!D10,"") -> -0.96500921 | E22: =IFERROR(E20/Saipem_IS!E10,"") -> 0.26781857 | F22: =IFERROR(F20/Saipem_IS!F10,"") -> 0.5696012 | G22: =IFERROR(G20/Saipem_IS!G10,"") -> 0.72319347
A23: Capex intensity (Capex / Revenue) | B23: =-B15/Saipem_IS!B4 -> 0.04385726 | C23: =-C15/Saipem_IS!C4 -> 0.04564951 | D23: =-D15/Saipem_IS!D4 -> 0.05240481 | E23: =-E15/Saipem_IS!E4 -> 0.040592892 | F23: =-F15/Saipem_IS!F4 -> 0.023163104 | G23: =-G15/Saipem_IS!G4 -> 0.023488417

Sheet Saipem_Segments
A1: SAIPEM — SEGMENTS (€ million, current segmentation: ABS / Energy Carriers / Drilling)
B3: 2020 | C3: 2021 | D3: 2022 | E3: 2023 | F3: 2024 | G3: 2025
A4: REVENUE BY SEGMENT
A5: Asset Based Services | E5: 6700 | F5: 8058 | G5: 9044
A6: Energy Carriers | E6: 4443 | F6: 5573 | G6: 5624
A7: Offshore Drilling | E7: 731 | F7: 918 | G7: 829
A8: Legacy: Offshore E&C | B8: 4801 | C8: 4415 | D8: 6440
A9: Legacy: Onshore E&C | B9: 1954 | C9: 1898 | D9: 3018
A10: Legacy: Offshore Drilling | B10: 386 | C10: 415 | D10: 522
A11: Legacy: Onshore Drilling (divested) | B11: 201 | C11: 147
A13: ADJUSTED EBITDA BY SEGMENT
A14: Asset Based Services | F14: 954 | G14: 1299
A15: Energy Carriers | F15: 40 | G15: 100
A16: Offshore Drilling | F16: 335 | G16: 317

Sheet Saipem_Backlog
A1: SAIPEM — BACKLOG & NEW CONTRACTS (€ million)
B3: 2020 | C3: 2021 | D3: 2022 | E3: 2023 | F3: 2024 | G3: 2025
A4: New contracts awarded during year | B4: 8659 | C4: 7208 | D4: 12941 | E4: 17659 | F4: 18812 | G4: 12936
A5: Backlog at year-end (consolidated) | B5: 22400 | C5: 22733 | D5: 24017 | E5: 29802 | F5: 34065 | G5: 31469
A7: Book-to-bill (New orders / Revenue) | B7: =B4/Saipem_IS!B4 -> 1.1793789 | C7: =C4/Saipem_IS!C4 -> 1.1041667 | D7: =D4/Saipem_IS!D4 -> 1.2966934 | E7: =E4/Saipem_IS!E4 -> 1.4871989 | F7: =F4/Saipem_IS!F4 -> 1.2930098 | G7: =G4/Saipem_IS!G4 -> 0.83474221
A8: Backlog / Revenue (years of coverage) | B8: =B5/Saipem_IS!B4 -> 3.0509398 | C8: =C5/Saipem_IS!C4 -> 3.4823836 | D8: =D5/Saipem_IS!D4 -> 2.406513 | E8: =E5/Saipem_IS!E4 -> 2.5098535 | F8: =F5/Saipem_IS!F4 -> 2.341398 | G8: =G5/Saipem_IS!G4 -> 2.0306511
A10: 2025 BACKLOG BY SEGMENT (€ million)
A11: Asset Based Services | B11: 21163
A12: Energy Carriers | B12: 9345
A13: Offshore Drilling | B13: 961

Sheet Saipem_KPI
A1: SAIPEM — KEY RATIOS (computed)
B3: 2020 | C3: 2021 | D3: 2022 | E3: 2023 | F3: 2024 | G3: 2025
A4: Revenue (€ m) | B4: =Saipem_IS!B4 -> 7342 | C4: =Saipem_IS!C4 -> 6528 | D4: =Saipem_IS!D4 -> 9980 | E4: =Saipem_IS!E4 -> 11874 | F4: =Saipem_IS!F4 -> 14549 | G4: =Saipem_IS!G4 -> 15497
A5: EBITDA (€ m) | B5: =Saipem_IS!B10 -> 428 | C5: =Saipem_IS!C10 -> -1724 | D5: =Saipem_IS!D10 -> 543 | E5: =Saipem_IS!E10 -> 926 | F5: =Saipem_IS!F10 -> 1329 | G5: =Saipem_IS!G10 -> 1716
A6: EBITDA margin | B6: =Saipem_IS!B10/Saipem_IS!B4 -> 0.058294743 | C6: =Saipem_IS!C10/Saipem_IS!C4 -> -0.26409314 | D6: =Saipem_IS!D10/Saipem_IS!D4 -> 0.054408818 | E6: =Saipem_IS!E10/Saipem_IS!E4 -> 0.077985515 | F6: =Saipem_IS!F10/Saipem_IS!F4 -> 0.091346484 | G6: =Saipem_IS!G10/Saipem_IS!G4 -> 0.11073111
A7: FCF (€ m) | B7: =Saipem_CF!B20 -> -187 | C7: =Saipem_CF!C20 -> -193 | D7: =Saipem_CF!D20 -> -524 | E7: =Saipem_CF!E20 -> 248 | F7: =Saipem_CF!F20 -> 757 | G7: =Saipem_CF!G20 -> 1241
A8: Net debt post-IFRS 16 (€ m) | B8: =Saipem_BS!B21 -> 1226 | C8: =Saipem_BS!C21 -> 1541 | D8: =Saipem_BS!D21 -> 264 | E8: =Saipem_BS!E21 -> 261 | F8: =Saipem_BS!F21 -> -23 | G8: =Saipem_BS!G21 -> 272
A9: Net debt / EBITDA | B9: =IFERROR(Saipem_BS!B21/Saipem_IS!B10,"") -> 2.864486 | C9: =IFERROR(Saipem_BS!C21/Saipem_IS!C10,"") -> -0.89385151 | D9: =IFERROR(Saipem_BS!D21/Saipem_IS!D10,"") -> 0.48618785 | E9: =IFERROR(Saipem_BS!E21/Saipem_IS!E10,"") -> 0.28185745 | F9: =IFERROR(Saipem_BS!F21/Saipem_IS!F10,"") -> -0.017306245 | G9: =IFERROR(Saipem_BS!G21/Saipem_IS!G10,"") -> 0.15850816
A10: Backlog / Revenue | B10: =Saipem_Backlog!B5/Saipem_IS!B4 -> 3.0509398 | C10: =Saipem_Backlog!C5/Saipem_IS!C4 -> 3.4823836 | D10: =Saipem_Backlog!D5/Saipem_IS!D4 -> 2.406513 | E10: =Saipem_Backlog!E5/Saipem_IS!E4 -> 2.5098535 | F10: =Saipem_Backlog!F5/Saipem_IS!F4 -> 2.341398 | G10: =Saipem_Backlog!G5/Saipem_IS!G4 -> 2.0306511
A11: Book-to-bill | B11: =Saipem_Backlog!B4/Saipem_IS!B4 -> 1.1793789 | C11: =Saipem_Backlog!C4/Saipem_IS!C4 -> 1.1041667 | D11: =Saipem_Backlog!D4/Saipem_IS!D4 -> 1.2966934 | E11: =Saipem_Backlog!E4/Saipem_IS!E4 -> 1.4871989 | F11: =Saipem_Backlog!F4/Saipem_IS!F4 -> 1.2930098 | G11: =Saipem_Backlog!G4/Saipem_IS!G4 -> 0.83474221

Sheet Subsea7_IS
A1: SUBSEA 7 — CONSOLIDATED INCOME STATEMENT ($ million)
B3: 2020 | C3: 2021 | D3: 2022 | E3: 2023 | F3: 2024 | G3: 2025
A4: Revenue | B4: 3466.4 | C4: 5010 | D4: 5135.8 | E4: 5973.7 | F4: 6837 | G4: 7086.3
A5: Operating expenses | B5: -3652.9 | C5: -4714.2 | D5: -4794.4 | E5: -5610.9 | F5: -6132.3 | G5: -6011.4
A6: Reversal of impairment on PP&E | B6: 0 | C6: 0 | D6: 55.6 | E6: 0 | F6: 0 | G6: 0
A7: Gross profit (loss) | B7: -186.5 | C7: 295.8 | D7: 397 | E7: 362.8 | F7: 704.7 | G7: 1074.9
A8: Administrative expenses | B8: -241.4 | C8: -228 | D8: -245.2 | E8: -266.3 | F8: -297.2 | G8: -340.5
A9: Impairment of goodwill | B9: -605.4 | C9: 0 | D9: 0 | E9: 0 | F9: 0 | G9: 0
A10: Share of net income (loss) of associates & JVs | B10: -0.5 | C10: 3.9 | D10: -3 | E10: 8.2 | F10: 38 | G10: 36.3
A11: Net operating income (loss) | B11: -1033.8 | C11: 71.7 | D11: 148.8 | E11: 104.7 | F11: 445.5 | G11: 770.7
A12: Finance income | B12: 4.8 | C12: 4.7 | D12: 9 | E12: 25.2 | F12: 24.4 | G12: 22.8
A13: Other gains and losses | B13: -18.3 | C13: 44.4 | D13: 1.9 | E13: 21.3 | F13: -0.5 | G13: -84.4
A14: Finance costs | B14: -24.6 | C14: -20.1 | D14: -23.4 | E14: -71.2 | F14: -101.2 | G14: -87.3
A15: Income (loss) before taxes | B15: -1071.9 | C15: 100.7 | D15: 136.3 | E15: 80 | F15: 368.2 | G15: 621.8
... A19: Adjusted EBITDA | B19: 337.1 | C19: 520.9 | D19: 559.4 | E19: 714.4 | F19: 1090.1 | G19: 1480.4
A21: MARGINS
A22: Adjusted EBITDA margin | B22: =B19/B4 -> 0.097247865 | C22: =C19/C4 -> 0.10397206 | D22: =D19/D4 -> 0.10892169 | E22: =E19/E4 -> 0.11959087 | F22: =F19/F4 -> 0.15944128 | G22: =G19/G4 -> 0.20891015
A23: Net operating income margin | B23: =B11/B4 -> -0.29823448 | C23: =C11/C4 -> 0.014311377 | D23: =D11/D4 -> 0.028973091 | E23: =E11/E4 -> 0.017526826 | F23: =F11/F4 -> 0.065160158 | G23: =G11/G4 -> 0.10875915
A24: Net income margin | B24: =B17/B4 -> -0.31883222 | C24: =C17/C4 -> 0.0072654691 | D24: =D17/D4 -> 0.0070875034 | E24: =E17/E4 -> 0.0016740044 | F24: =F17/F4 -> 0.031680562 | G24: =G17/G4 -> 0.05703964
A25: Revenue YoY growth | C25: =C4/B4-1 -> 0.44530348 | D25: =D4/C4-1 -> 0.02510978 | E25: =E4/D4-1 -> 0.16314888 | F25: =F4/E4-1 -> 0.1445168 | G25: =G4/F4-1 -> 0.036463361

Sheet Subsea7_BS
A1: SUBSEA 7 — CONSOLIDATED BALANCE SHEET ($ million, as of 31 December)
B3: 2020 | C3: 2021 | D3: 2022 | E3: 2023 | F3: 2024 | G3: 2025
A4: ASSETS
A5: Goodwill | B5: 84.5 | C5: 160.5 | D5: 191.3 | E5: 192.2 | F5: 183.7 | G5: 157
A6: Intangible assets | B6: 46 | C6: 37.3 | D6: 31.1 | E6: 58.5 | F6: 87.6 | G6: 111.7
A7: Property, plant and equipment | B7: 3982.6 | C7: 4081 | D7: 3922 | E7: 4070 | F7: 3960.8 | G7: 3760.2
A8: Right-of-use assets | B8: 213.3 | C8: 206.4 | D8: 242 | E8: 419.4 | F8: 400.3 | G8: 309.5
A9: Interests in associates & JVs | B9: 29.5 | C9: 28.6 | D9: 25.5 | E9: 342 | F9: 367.2 | G9: 370.2
A10: Other non-current assets | B10: 104.8 | C10: 145.5 | D10: 111 | E10: 158.5 | F10: 206.7 | G10: 200.8
A11: Total non-current assets | B11: 4461.7 | C11: 4660.3 | D11: 4522.9 | E11: 5230.6 | F11: 5206.3 | G11: 4909.7
A12: Cash and cash equivalents | B12: 511.6 | C12: 597.6 | D12: 645.6 | E12: 750.9 | F12: 575.3 | G12: 969.7
A13: Other current assets | B13: 1323.8 | C13: 1730.4 | D13: 1775.7 | E13: 2114 | F13: 1898.8 | G13: 2151.1
A14: Total current assets | B14: 1835.4 | C14: 2328 | D14: 2421.3 | E14: 2864.9 | F14: 2474.1 | G14: 3120.8
A15: TOTAL ASSETS | B15: 6297.1 | C15: 6988.3 | D15: 6944.2 | E15: 8095.5 | F15: 7680.4 | G15: 8030.5
A17: EQUITY & LIABILITIES
A18: Equity attributable to shareholders | B18: 4227.8 | C18: 4183.8 | D18: 4121.6 | E18: 4323 | F18: 4250.4 | G18: 4406.3
A19: Non-controlling interests | B19: 27.3 | C19: 305.4 | D19: 329.1 | E19: 34.1 | F19: 44.6 | G19: 38.5
A20: Total equity | B20: 4255.1 | C20: 4489.2 | D20: 4450.7 | E20: 4357.1 | F20: 4295 | G20: 4444.8
A21: Non-current borrowings | B21: 184.4 | C21: 360.3 | D21: 302.2 | E21: 721.4 | F21: 583.8 | G21: 402.4
A22: Non-current lease liabilities | B22: 168.6 | C22: 142.9 | D22: 161.2 | E22: 290.5 | F22: 231.1 | G22: 184.9
A23: Other non-current liabilities | B23: 137.8 | C23: 134.4 | D23: 145.7 | E23: 110.4 | F23: 136.6 | G23: 180
A24: Total non-current liabilities | B24: 490.8 | C24: 637.6 | D24: 609.1 | E24: 1122.3 | F24: 951.5 | G24: 767.3
A25: Current portion of borrowings | B25: 24.6 | C25: 61.6 | D25: 53.8 | E25: 123.5 | F25: 138.2 | G25: 181.3
A26: Current portion of lease liabilities | B26: 85.4 | C26: 88 | D26: 95.8 | E26: 167.8 | F26: 223.8 | G26: 164.9
A27: Other current liabilities | B27: 1441.2 | C27: 1711.9 | D27: 1734.8 | E27: 2324.8 | F27: 2071.9 | G27: 2472.2
A28: Total current liabilities | B28: 1551.2 | C28: 1861.5 | D28: 1884.4 | E28: 2616.1 | F28: 2433.9 | G28: 2818.4
A29: TOTAL LIABILITIES | B29: 2042 | C29: 2499.1 | D29: 2493.5 | E29: 3738.4 | F29: 3385.4 | G29: 3585.7
A31: NET DEBT COMPUTATION
A32: Gross debt (borrowings only, ex-lease) | B32: =B21+B25 -> 209 | C32: =C21+C25 -> 421.9 | D32: =D21+D25 -> 356 | E32: =E21+E25 -> 844.9 | F32: =F21+F25 -> 722 | G32: =G21+G25 -> 583.7
A33: Net debt (cash) pre-IFRS 16 | B33: =B32-B12 -> -302.6 | C33: =C32-C12 -> -175.7 | D33: =D32-D12 -> -289.6 | E33: =E32-E12 -> 94 | F33: =F32-F12 -> 146.7 | G33: =G32-G12 -> -386
A34: Lease liabilities | B34: =B22+B26 -> 254 | C34: =C22+C26 -> 230.9 | D34: =D22+D26 -> 257 | E34: =E22+E26 -> 458.3 | F34: =F22+F26 -> 454.9 | G34: =G22+G26 -> 349.8
A35: Net debt post-IFRS 16 | B35: =B33+B34 -> -48.6 | C35: =C33+C34 -> 55.2 | D35: =D33+D34 -> -32.6 | E35: =E33+E34 -> 552.3 | F35: =F33+F34 -> 601.6 | G35: =G33+G34 -> -36.2

Sheet Subsea7_CF
A1: SUBSEA 7 — CASH FLOW ($ million)
B3: 2020 | C3: 2021 | D3: 2022 | E3: 2023 | F3: 2024 | G3: 2025
A4: Net cash generated from operating activities | B4: 446.8 | C4: 293 | D4: 485.8 | E4: 660 | F4: 931.4 | G4: 1470.7
A5: Capital expenditure (PP&E + intangibles) | B5: -182.6 | C5: -157.7 | D5: -231 | E5: -581.2 | F5: -348.7 | G5: -281
A6: Net cash used in investing activities (total) | B6: -164.6 | C6: -183.7 | D6: -220.1 | E6: -710.2 | F6: -413.6 | G6: -213.6
A7: Net cash used in financing activities | B7: -157.6 | C7: -22.8 | D7: -211.2 | E7: -280.3 | F7: -696.4 | G7: -874
A8: Cash and cash equivalents at year-end | B8: 511.6 | C8: 597.6 | D8: 645.6 | E8: 750.9 | F8: 575.3 | G8: 969.7
A10: Free cash flow (CFO + Capex) | B10: =B4+B5 -> 264.2 | C10: =C4+C5 -> 135.3 | D10: =D4+D5 -> 254.8 | E10: =E4+E5 -> 78.8 | F10: =F4+F5 -> 582.7 | G10: =G4+G5 -> 1189.7
A12: FCF conversion (FCF / Adj EBITDA) | B12: =IFERROR(B10/Subsea7_IS!B19,"") -> 0.7837437 | C12: =IFERROR(C10/Subsea7_IS!C19,"") -> 0.25974275 | D12: =IFERROR(D10/Subsea7_IS!D19,"") -> 0.45548802 | E12: =IFERROR(E10/Subsea7_IS!E19,"") -> 0.11030235 | F12: =IFERROR(F10/Subsea7_IS!F19,"") -> 0.53453812 | G12: =IFERROR(G10/Subsea7_IS!G19,"") -> 0.80363415
A13: Capex intensity (Capex / Revenue) | B13: =-B5/Subsea7_IS!B4 -> 0.052677129 | C13: =-C5/Subsea7_IS!C4 -> 0.031477046 | D13: =-D5/Subsea7_IS!D4 -> 0.044978387 | E13: =-E5/Subsea7_IS!E4 -> 0.097293135 | F13: =-F5/Subsea7_IS!F4 -> 0.051001901 | G13: =-G5/Subsea7_IS!G4 -> 0.03965398

Sheet Subsea7_Backlog
A1: SUBSEA 7 — BACKLOG & ORDER INTAKE ($ million)
B3: 2020 | C3: 2021 | D3: 2022 | E3: 2023 | F3: 2024 | G3: 2025
A4: Order intake during year | B4: 4400 | C4: 6088.5 | D4: 7096.1 | E4: 7443.7 | F4: 8175.6 | G4: 9017.5
A5: Backlog at year-end | B5: 6214 | C5: 7212 | D5: 9008 | E5: 10587 | F5: 11175 | G5: 13769
A7: Book-to-bill (Intake / Revenue) | B7: =B4/Subsea7_IS!B4 -> 1.2693284 | C7: =C4/Subsea7_IS!C4 -> 1.2152695 | D7: =D4/Subsea7_IS!D4 -> 1.3816932 | E7: =E4/Subsea7_IS!E4 -> 1.2460786 | F7: =F4/Subsea7_IS!F4 -> 1.1957876 | G7: =G4/Subsea7_IS!G4 -> 1.2725259
A8: Backlog / Revenue | B8: =B5/Subsea7_IS!B4 -> 1.7926379 | C8: =C5/Subsea7_IS!C4 -> 1.439521 | D8: =D5/Subsea7_IS!D4 -> 1.7539624 | E8: =E5/Subsea7_IS!E4 -> 1.7722684 | F8: =F5/Subsea7_IS!F4 -> 1.6344888 | G8: =G5/Subsea7_IS!G4 -> 1.943045

Sheet Subsea7_KPI
A1: SUBSEA 7 — KEY RATIOS (computed)
B3: 2020 | C3: 2021 | D3: 2022 | E3: 2023 | F3: 2024 | G3: 2025
A4: Revenue ($ m) | B4: =Subsea7_IS!B4 -> 3466.4 | C4: =Subsea7_IS!C4 -> 5010 | D4: =Subsea7_IS!D4 -> 5135.8 | E4: =Subsea7_IS!E4 -> 5973.7 | F4: =Subsea7_IS!F4 -> 6837 | G4: =Subsea7_IS!G4 -> 7086.3
A5: Adjusted EBITDA ($ m) | B5: =Subsea7_IS!B19 -> 337.1 | C5: =Subsea7_IS!C19 -> 520.9 | D5: =Subsea7_IS!D19 -> 559.4 | E5: =Subsea7_IS!E19 -> 714.4 | F5: =Subsea7_IS!F19 -> 1090.1 | G5: =Subsea7_IS!G19 -> 1480.4
A6: Adj EBITDA margin | B6: =Subsea7_IS!B19/Subsea7_IS!B4 -> 0.097247865 | C6: =Subsea7_IS!C19/Subsea7_IS!C4 -> 0.10397206 | D6: =Subsea7_IS!D19/Subsea7_IS!D4 -> 0.10892169 | E6: =Subsea7_IS!E19/Subsea7_IS!E4 -> 0.11959087 | F6: =Subsea7_IS!F19/Subsea7_IS!F4 -> 0.15944128 | G6: =Subsea7_IS!G19/Subsea7_IS!G4 -> 0.20891015
A7: FCF ($ m) | B7: =Subsea7_CF!B10 -> 264.2 | C7: =Subsea7_CF!C10 -> 135.3 | D7: =Subsea7_CF!D10 -> 254.8 | E7: =Subsea7_CF!E10 -> 78.8 | F7: =Subsea7_CF!F10 -> 582.7 | G7: =Subsea7_CF!G10 -> 1189.7
A8: Net debt post-IFRS 16 ($ m) | B8: =Subsea7_BS!B35 -> -48.6 | C8: =Subsea7_BS!C35 -> 55.2 | D8: =Subsea7_BS!D35 -> -32.6 | E8: =Subsea7_BS!E35 -> 552.3 | F8: =Subsea7_BS!F35 -> 601.6 | G8: =Subsea7_BS!G35 -> -36.2
A9: Net debt / Adj EBITDA | B9: =IFERROR(Subsea7_BS!B35/Subsea7_IS!B19,"") -> -0.14417087 | C9: =IFERROR(Subsea7_BS!C35/Subsea7_IS!C19,"") -> 0.10597044 | D9: =IFERROR(Subsea7_BS!D35/Subsea7_IS!D19,"") -> -0.058276725 | E9: =IFERROR(Subsea7_BS!E35/Subsea7_IS!E19,"") -> 0.7730963 | F9: =IFERROR(Subsea7_BS!F35/Subsea7_IS!F19,"") -> 0.55187597 | G9: =IFERROR(Subsea7_BS!G35/Subsea7_IS!G19,"") -> -0.024452851
A10: Backlog / Revenue | B10: =Subsea7_Backlog!B5/Subsea7_IS!B4 -> 1.7926379 | C10: =Subsea7_Backlog!C5/Subsea7_IS!C4 -> 1.439521 | D10: =Subsea7_Backlog!D5/Subsea7_IS!D4 -> 1.7539624 | E10: =Subsea7_Backlog!E5/Subsea7_IS!E4 -> 1.7722684 | F10: =Subsea7_Backlog!F5/Subsea7_IS!F4 -> 1.6344888 | G10: =Subsea7_Backlog!G5/Subsea7_IS!G4 -> 1.943045
A11: Book-to-bill | B11: =Subsea7_Backlog!B4/Subsea7_IS!B4 -> 1.2693284 | C11: =Subsea7_Backlog!C4/Subsea7_IS!C4 -> 1.2152695 | D11: =Subsea7_Backlog!D4/Subsea7_IS!D4 -> 1.3816932 | E11: =Subsea7_Backlog!E4/Subsea7_IS!E4 -> 1.2460786 | F11: =Subsea7_Backlog!F4/Subsea7_IS!F4 -> 1.1957876 | G11: =Subsea7_Backlog!G4/Subsea7_IS!G4 -> 1.2725259

Sheet Comparison
A1: SIDE-BY-SIDE COMPARISON (all figures in USD millions; Saipem converted at annual average FX)
B3: 2020 | C3: 2021 | D3: 2022 | E3: 2023 | F3: 2024 | G3: 2025
A4: REVENUE ($ m)
A5: Saipem (€ converted @ avg FX) | B5: =Saipem_IS!B4*FX!B5 -> 8386.0324 | C5: =Saipem_IS!C4*FX!C5 -> 7720.6656 | D5: =Saipem_IS!D4*FX!D5 -> 10508.94 | E5: =Saipem_IS!E4*FX!E5 -> 12839.356 | F5: =Saipem_IS!F4*FX!F5 -> 15747.838 | G5: =Saipem_IS!G4*FX!G5 -> 17558.101
A6: Subsea 7 | B6: =Subsea7_IS!B4 -> 3466.4 | C6: =Subsea7_IS!C4 -> 5010 | D6: =Subsea7_IS!D4 -> 5135.8 | E6: =Subsea7_IS!E4 -> 5973.7 | F6: =Subsea7_IS!F4 -> 6837 | G6: =Subsea7_IS!G4 -> 7086.3
A7: Saipem / Subsea 7 (ratio) | B7: =B5/B6 -> 2.4192339 | C7: =C5/C6 -> 1.541051 | D7: =D5/D6 -> 2.0462129 | E7: =E5/E6 -> 2.1493139 | F7: =F5/F6 -> 2.3033257 | G7: =G5/G6 -> 2.477753
A9: EBITDA ($ m) — Saipem reported EBITDA; Subsea7 Adj EBITDA
A10: Saipem (€ converted @ avg FX) | B10: =Saipem_IS!B10*FX!B5 -> 488.8616 | C10: =Saipem_IS!C10*FX!C5 -> -2038.9748 | D10: =Saipem_IS!D10*FX!D5 -> 571.779 | E10: =Saipem_IS!E10*FX!E5 -> 1001.2838 | F10: =Saipem_IS!F10*FX!F5 -> 1438.5096 | G10: =Saipem_IS!G10*FX!G5 -> 1944.228
A11: Subsea 7 (Adj EBITDA) | B11: =Subsea7_IS!B19 -> 337.1 | C11: =Subsea7_IS!C19 -> 520.9 | D11: =Subsea7_IS!D19 -> 559.4 | E11: =Subsea7_IS!E19 -> 714.4 | F11: =Subsea7_IS!F19 -> 1090.1 | G11: =Subsea7_IS!G19 -> 1480.4
A13: NET DEBT POST-IFRS 16 ($ m, year-end FX)
A14: Saipem (€ converted @ year-end FX) | B14: =Saipem_BS!B21*FX!B4 -> 1504.4246 | C14: =Saipem_BS!C21*FX!C4 -> 1745.3366 | D14: =Saipem_BS!D21*FX!D4 -> 281.5824 | E14: =Saipem_BS!E21*FX!E4 -> 288.405 | F14: =Saipem_BS!F21*FX!F4 -> -23.8947 | G14: =Saipem_BS!G21*FX!G4 -> 321.776
A15: Subsea 7 | B15: =Subsea7_BS!B35 -> -48.6 | C15: =Subsea7_BS!C35 -> 55.2 | D15: =Subsea7_BS!D35 -> -32.6 | E15: =Subsea7_BS!E35 -> 552.3 | F15: =Subsea7_BS!F35 -> 601.6 | G15: =Subsea7_BS!G35 -> -36.2
A17: BACKLOG ($ m, year-end FX)
A18: Saipem (€ converted @ year-end FX) | B18: =Saipem_Backlog!B5*FX!B4 -> 27487.04 | C18: =Saipem_Backlog!C5*FX!C4 -> 25747.396 | D18: =Saipem_Backlog!D5*FX!D4 -> 25616.532 | E18: =Saipem_Backlog!E5*FX!E4 -> 32931.21 | F18: =Saipem_Backlog!F5*FX!F4 -> 35390.128 | G18: =Saipem_Backlog!G5*FX!G4 -> 37227.827
A19: Subsea 7 | B19: =Subsea7_Backlog!B5 -> 6214 | C19: =Subsea7_Backlog!C5 -> 7212 | D19: =Subsea7_Backlog!D5 -> 9008 | E19: =Subsea7_Backlog!E5 -> 10587 | F19: =Subsea7_Backlog!F5 -> 11175 | G19: =Subsea7_Backlog!G5 -> 13769
A21: COMBINED (indicative — no synergies, no eliminations)
A22: Combined revenue ($ m) | B22: =Saipem_IS!B4*FX!B5+Subsea7_IS!B4 -> 11852.432 | C22: =Saipem_IS!C4*FX!C5+Subsea7_IS!C4 -> 12730.666 | D22: =Saipem_IS!D4*FX!D5+Subsea7_IS!D4 -> 15644.74 | E22: =Saipem_IS!E4*FX!E5+Subsea7_IS!E4 -> 18813.056 | F22: =Saipem_IS!F4*FX!F5+Subsea7_IS!F4 -> 22584.838 | G22: =Saipem_IS!G4*FX!G5+Subsea7_IS!G4 -> 24644.401
A23: Combined backlog ($ m, year-end) | B23: =Saipem_Backlog!B5*FX!B4+Subsea7_Backlog!B5 -> 33701.04 | C23: =Saipem_Backlog!C5*FX!C4+Subsea7_Backlog!C5 -> 32959.396 | D23: =Saipem_Backlog!D5*FX!D4+Subsea7_Backlog!D5 -> 34624.532 | E23: =Saipem_Backlog!E5*FX!E4+Subsea7_Backlog!E5 -> 43518.21 | F23: =Saipem_Backlog!F5*FX!F4+Subsea7_Backlog!F5 -> 46565.128 | G23: =Saipem_Backlog!G5*FX!G4+Subsea7_Backlog!G5 -> 50996.827
